osbot_fast_api_serverless/__init__.py
osbot_fast_api_serverless/deploy/Deploy__Serverless__Fast_API.py
osbot_fast_api_serverless/deploy/Schema__AWS_Setup__Serverless__Fast_API.py
osbot_fast_api_serverless/deploy/__init__.py
osbot_fast_api_serverless/fast_api/Serverless__Fast_API.py
osbot_fast_api_serverless/fast_api/Serverless__Fast_API__Config.py
osbot_fast_api_serverless/fast_api/__init__.py
osbot_fast_api_serverless/fast_api/lambda_handler.py
osbot_fast_api_serverless/fast_api/routes/Routes__Info.py
osbot_fast_api_serverless/fast_api/routes/__init__.py
osbot_fast_api_serverless/services/info/Service_Info.py
osbot_fast_api_serverless/services/info/__init__.py
osbot_fast_api_serverless/services/info/schemas/Enum__Service_Environment.py
osbot_fast_api_serverless/services/info/schemas/Enum__Service_Status.py
osbot_fast_api_serverless/services/info/schemas/Schema__Server__Versions.py
osbot_fast_api_serverless/services/info/schemas/Schema__Service__Status.py
osbot_fast_api_serverless/services/info/schemas/__init__.py
osbot_fast_api_serverless/utils/Version.py
osbot_fast_api_serverless/utils/__init__.py
osbot_fast_api_serverless/utils/testing/__init__.py
osbot_fast_api_serverless/utils/testing/skip_tests.py
osbot_fast_api_serverless/version
osbot_fast_api_serverless-1.33.0.dist-info/LICENSE
osbot_fast_api_serverless-1.33.0.dist-info/METADATA
osbot_fast_api_serverless-1.33.0.dist-info/WHEEL
osbot_fast_api_serverless-1.33.0.dist-info/RECORD
