Metadata-Version: 2.1
Name: osbot_fast_api_serverless
Version: 1.33.0
Summary: OSBot-Fast-API-Serverless
Home-page: https://github.com/owasp-sbot/OSBot-Fast-API-Serverless
License: Apache 2.0
Author: Dinis Cruz
Author-email: dinis.cruz@owasp.org
Requires-Python: >=3.12,<4.0
Classifier: License :: Other/Proprietary License
Classifier: Programming Language :: Python :: 3
Classifier: Programming Language :: Python :: 3.12
Requires-Dist: mangum
Requires-Dist: osbot-aws
Requires-Dist: osbot-fast-api
Project-URL: Repository, https://github.com/owasp-sbot/OSBot-Fast-API-Serverless
